{
  "schemaVersion": "runtime-asset-authoring-summary.v1",
  "authoringSource": "mpfb2",
  "kind": "garment",
  "variantId": "male-base",
  "garment": {
    "name": "mpfb-male-base.male_casualsuit02",
    "vertexCount": 2136,
    "materialSlots": [
      "mpfb-male-base.male_casualsuit02"
    ],
    "vertexGroups": [
      "pelvis",
      "spine_01",
      "spine_02",
      "spine_03",
      "clavicle_l",
      "upperarm_l",
      "lowerarm_l",
      "hand_l",
      "thumb_01_l",
      "clavicle_r",
      "upperarm_r",
      "lowerarm_r",
      "hand_r",
      "thumb_01_r",
      "neck_01",
      "head",
      "thigh_l",
      "calf_l",
      "foot_l",
      "thigh_r",
      "calf_r",
      "foot_r"
    ]
  },
  "fitAudit": {
    "minDistanceMeters": 0.0025948546826839447,
    "penetratingVertexCount": 0,
    "thresholdCounts": {
      "0.001": 0,
      "0.003": 32,
      "0.005": 36,
      "0.01": 54
    },
    "hotSpots": [
      {
        "zone": "arms",
        "countWithin5mm": 22
      },
      {
        "zone": "calves",
        "countWithin5mm": 11
      },
      {
        "zone": "chest",
        "countWithin5mm": 3
      }
    ]
  },
  "armature": {
    "name": "mpfb-male-base",
    "boneNames": [
      "Root",
      "pelvis",
      "spine_01",
      "spine_02",
      "spine_03",
      "clavicle_l",
      "upperarm_l",
      "lowerarm_l",
      "hand_l",
      "index_01_l",
      "index_02_l",
      "index_03_l",
      "middle_01_l",
      "middle_02_l",
      "middle_03_l",
      "pinky_01_l",
      "pinky_02_l",
      "pinky_03_l",
      "ring_01_l",
      "ring_02_l",
      "ring_03_l",
      "thumb_01_l",
      "thumb_02_l",
      "thumb_03_l",
      "clavicle_r",
      "upperarm_r",
      "lowerarm_r",
      "hand_r",
      "index_01_r",
      "index_02_r",
      "index_03_r",
      "middle_01_r",
      "middle_02_r",
      "middle_03_r",
      "pinky_01_r",
      "pinky_02_r",
      "pinky_03_r",
      "ring_01_r",
      "ring_02_r",
      "ring_03_r",
      "thumb_01_r",
      "thumb_02_r",
      "thumb_03_r",
      "neck_01",
      "head",
      "thigh_l",
      "calf_l",
      "foot_l",
      "ball_l",
      "thigh_r",
      "calf_r",
      "foot_r",
      "ball_r"
    ]
  },
  "preset": {
    "presetId": "male-base",
    "relativePath": "authoring/avatar/mpfb/presets/male-base.json"
  },
  "clothesAsset": {
    "kind": "mpfb-user-data-fragment",
    "value": "clothes/male_casualsuit02/male_casualsuit02.mhclo"
  },
  "packState": {
    "installed": true,
    "modern": true,
    "installedNow": false,
    "userDataSource": "blender-extension-user-data"
  },
  "patternSpec": {
    "relativePath": "authoring/garments/mpfb/specs/top_city_relaxed.pattern-spec.json"
  },
  "outputBlend": "authoring/garments/exports/raw/mpfb-male-top_city_relaxed.blend",
  "outputGlb": "apps/web/public/assets/garments/mpfb/male/top_city_relaxed.glb",
  "materialProfile": {
    "relativePath": "authoring/garments/mpfb/specs/top_city_relaxed.material-profile.json"
  },
  "simProxy": {
    "relativePath": "authoring/garments/mpfb/specs/top_city_relaxed.sim-proxy.json"
  },
  "collisionProxy": {
    "relativePath": "authoring/garments/mpfb/specs/top_city_relaxed.collision-proxy.json"
  },
  "hqArtifact": {
    "relativePath": "authoring/garments/mpfb/specs/top_city_relaxed.hq-artifact.json"
  }
}
