{
  "schemaVersion": "runtime-asset-authoring-summary.v1",
  "authoringSource": "mpfb2",
  "kind": "hair",
  "variantId": "female-base",
  "hairStyle": "ponytail01",
  "armature": "mpfb-female-base",
  "objects": [
    {
      "name": "FS.Hair.ponytail01",
      "vertices": 3718,
      "materials": [
        "FS_Hair_ponytail01"
      ]
    }
  ],
  "outputBlend": "authoring/garments/exports/raw/mpfb-female-hair_signature_ponytail.blend",
  "outputGlb": "apps/web/public/assets/garments/mpfb/female/hair_signature_ponytail.glb"
}
